<?xml version="1.0" encoding="UTF-8" standalone="yes"?>
<persons>
    <person id="ed4ba0e9-5b5d-499d-90de-d054a4b728a8">
        <secondName>Ivanov</secondName>
        <firstName>Ivan</firstName>
        <lastName>Ivanovich</lastName>
        <jobTittle>
            <uuid>bc074d88-bd04-4b34-833b-ea2fb7a9139a</uuid>
            <jobTittleName>Java middle</jobTittleName>
        </jobTittle>
        <birthDay>1979-04-30T23:40:05.360+03:00</birthDay>
        <phoneNumber>687546346</phoneNumber>
        <photo>http//:dssf.png</photo>
    </person>
    <person id="32b44539-e795-4b14-9dd6-519b29fd4dd5">
        <secondName>Migranov</secondName>
        <firstName>Salavat</firstName>
        <lastName>Vagizovich</lastName>
        <jobTittle>
            <uuid>e29ded9a-dcda-4db1-ab5a-5de4fc407947</uuid>
            <jobTittleName>Java junior</jobTittleName>
        </jobTittle>
        <birthDay>1976-12-17T22:11:57.099+03:00</birthDay>
        <phoneNumber>897546346</phoneNumber>
        <photo>http//:migsal.png</photo>
    </person>
    <person id="0f8fb8fb-d017-40ca-8863-1881aa083b9a">
        <secondName>Kondratyuk</secondName>
        <firstName>Aleksandr</firstName>
        <lastName>Petrovich</lastName>
        <jobTittle>
            <uuid>11aa7f92-3cca-46a3-85ed-4d4bc6f266e2</uuid>
            <jobTittleName>QA</jobTittleName>
        </jobTittle>
        <birthDay>1947-05-02T11:58:24.399+03:00</birthDay>
        <phoneNumber>86436346</phoneNumber>
        <photo>http//:dsd.png</photo>
    </person>
    <person id="6f76bdf2-1bb4-4ed4-86af-afc648e9e634">
        <secondName>Yushko</secondName>
        <firstName>Oleg</firstName>
        <lastName>Yurevich</lastName>
        <jobTittle>
            <uuid>4741a084-34c1-48e9-b6a2-a358d268f3a8</uuid>
            <jobTittleName>QA junior</jobTittleName>
        </jobTittle>
        <birthDay>2009-11-24T18:38:47.972+03:00</birthDay>
        <phoneNumber>45345323</phoneNumber>
        <photo>http//:sdsf.png</photo>
    </person>
    <person id="8d228043-b513-4159-8746-f7afed38df70">
        <secondName>Petrosyan</secondName>
        <firstName>Sergey</firstName>
        <lastName>Uralovich</lastName>
        <jobTittle>
            <uuid>b40aefa3-a73b-443d-8547-e14e886e9b77</uuid>
            <jobTittleName>Alfresco junior</jobTittleName>
        </jobTittle>
        <birthDay>1974-11-12T21:40:27.598+03:00</birthDay>
        <phoneNumber>66787546346</phoneNumber>
        <photo>http//:hgh.png</photo>
    </person>
</persons>
